Metadata-Version: 2.1
Name: slc.mailrouter
Version: 3.0.1
Summary: Framework for handling email in zope
Home-page: https://github.com/syslabcom/slc.mailrouter
Author: Syslab.com GmbH
Author-email: info@syslab.com
License: GPL
Keywords: smtp2zope email mailin zope
Platform: UNKNOWN
Classifier: Programming Language :: Python
Classifier: Programming Language :: Python :: 2.7
Classifier: Programming Language :: Python :: 3.7
Classifier: Framework :: Plone
Classifier: Framework :: Plone :: 5.2
Provides-Extra: test
